Metadata-Version: 2.1
Name: micropython-scd30
Version: 0.2.0
Summary: MicroPython I2C driver for SCD30 CO2 sensor module
Home-page: https://github.com/agners/micropython-scd30
Author: Stefan Agner
Author-email: stefan@agner.ch
Maintainer: Stefan Agner
Maintainer-email: stefan@agner.ch
License: MIT
Keywords: scd30,co2,temperature,humidity,micropython,i2c
Platform: UNKNOWN
Classifier: Development Status :: 4 - Beta
Classifier: Programming Language :: Python :: Implementation :: MicroPython
Classifier: License :: OSI Approved :: MIT License
